skinny/__init__.py
skinny-0.0.1.dist-info/METADATA
skinny-0.0.1.dist-info/WHEEL
skinny-0.0.1.dist-info/top_level.txt
skinny-0.0.1.dist-info/RECORD
