Metadata-Version: 2.4
Name: skinny
Version: 0.0.1
Summary: A tree-based ui framework inspired by Flutter
Author: Warren Elrod
License: MIT
Classifier: Programming Language :: Python :: 3
Classifier: License :: OSI Approved :: MIT License
Classifier: Operating System :: OS Independent
Requires-Python: >=3.10
